Makefile
cmake_install.cmake
CMakeFiles/CMakeDirectoryInformation.cmake
CMakeFiles/progress.marks
UVLM/Makefile
UVLM/cmake_install.cmake
UVLM/libuvlm.so
UVLM/CMakeFiles/CMakeDirectoryInformation.cmake
UVLM/CMakeFiles/progress.marks
UVLM/CMakeFiles/uvlm.dir/DependInfo.cmake
UVLM/CMakeFiles/uvlm.dir/build.make
UVLM/CMakeFiles/uvlm.dir/cmake_clean.cmake
UVLM/CMakeFiles/uvlm.dir/compiler_depend.internal
UVLM/CMakeFiles/uvlm.dir/compiler_depend.make
UVLM/CMakeFiles/uvlm.dir/compiler_depend.ts
UVLM/CMakeFiles/uvlm.dir/depend.make
UVLM/CMakeFiles/uvlm.dir/flags.make
UVLM/CMakeFiles/uvlm.dir/link.txt
UVLM/CMakeFiles/uvlm.dir/progress.make
UVLM/CMakeFiles/uvlm.dir/src/cpp_interface.cpp.o
UVLM/CMakeFiles/uvlm.dir/src/cpp_interface.cpp.o.d
ic_sharpy-2.4.dist-info/licenses/LICENSE
sharpy/__init__.py
sharpy/sharpy_main.py
sharpy/version.py
sharpy/aero/__init__.py
sharpy/aero/models/__init__.py
sharpy/aero/models/aerogrid.py
sharpy/aero/models/grid.py
sharpy/aero/models/nonliftingbodygrid.py
sharpy/aero/utils/__init__.py
sharpy/aero/utils/airfoilpolars.py
sharpy/aero/utils/mapping.py
sharpy/aero/utils/utils.py
sharpy/aero/utils/uvlmlib.py
sharpy/cases/__init__.py
sharpy/cases/coupled/__init__.py
sharpy/cases/coupled/WindTurbine/__init__.py
sharpy/cases/coupled/WindTurbine/generate_rotor.py
sharpy/cases/coupled/X-HALE/generate_xhale.py
sharpy/cases/coupled/X-HALE/inputs/EMX-07_camber.txt
sharpy/cases/coupled/X-HALE/inputs/aero_properties.xlsx
sharpy/cases/coupled/X-HALE/inputs/beam_properties.xlsx
sharpy/cases/coupled/X-HALE/inputs/lumped_mass.xlsx
sharpy/cases/coupled/hinged_controlled_wing/__init__.py
sharpy/cases/coupled/hinged_controlled_wing/generate_hinged_controlled_wing.py
sharpy/cases/coupled/hinged_controlled_wing/generate_hinged_roll_controlled_wing.py
sharpy/cases/coupled/linear_horten/__init__.py
sharpy/cases/coupled/multibody_takeoff/__init__.py
sharpy/cases/coupled/multibody_takeoff/generate_hale.py
sharpy/cases/coupled/simple_HALE/__init__.py
sharpy/cases/coupled/simple_HALE/generate_hale.py
ic_sharpy-2.4.dist-info/METADATA
ic_sharpy-2.4.dist-info/WHEEL
ic_sharpy-2.4.dist-info/entry_points.txt
ic_sharpy-2.4.dist-info/top_level.txt
ic_sharpy-2.4.dist-info/RECORD
