Metadata-Version: 2.4
Name: ic_sharpy
Version: 2.4
Summary: SHARPy is a nonlinear aeroelastic analysis package developed at Imperial College London.
Home-page: https://github.com/ImperialCollegeLondon/sharpy
Author: 
Author-email: 
License: BSD-3-Clause
Project-URL: Homepage, https://github.com/ImperialCollegeLondon/sharpy
Keywords: nonlinear,aeroelastic,structural,aerodynamic,analysis
Classifier: Operating System :: MacOS
Classifier: Operating System :: POSIX :: Linux
Classifier: Programming Language :: Python :: 3.10
Classifier: Programming Language :: Fortran
Classifier: Programming Language :: C++
Requires-Python: >=3.8
License-File: LICENSE
Requires-Dist: numpy<2.0
Requires-Dist: configobj
Requires-Dist: h5py
Requires-Dist: scipy<1.14.0
Requires-Dist: sympy
Requires-Dist: matplotlib
Requires-Dist: colorama
Requires-Dist: dill
Requires-Dist: jupyterlab
Requires-External: mayavi@ git+https://github.com/enthought/mayavi.git
Requires-Dist: pandas
Requires-Dist: control
Requires-Dist: openpyxl>=3.0.10
Requires-Dist: lxml>=4.4.1
Requires-Dist: PySocks
Requires-Dist: PyYAML
Requires-Dist: jax
Provides-Extra: docs
Requires-Dist: sphinx; extra == "docs"
Requires-Dist: recommonmark>=0.6.0; extra == "docs"
Requires-Dist: sphinx_rtd_theme>=0.4.3; extra == "docs"
Requires-Dist: nbsphinx>=0.4.3; extra == "docs"
Provides-Extra: all
Requires-Dist: sphinx; extra == "all"
Requires-Dist: recommonmark>=0.6.0; extra == "all"
Requires-Dist: sphinx_rtd_theme>=0.4.3; extra == "all"
Requires-Dist: nbsphinx>=0.4.3; extra == "all"
Dynamic: home-page
Dynamic: license-file
Dynamic: requires-python
